database_automation/__init__.py
database_automation/mongo_crud.py
databaseConnectorUniversal-0.0.4.dist-info/LICENSE
databaseConnectorUniversal-0.0.4.dist-info/METADATA
databaseConnectorUniversal-0.0.4.dist-info/WHEEL
databaseConnectorUniversal-0.0.4.dist-info/top_level.txt
databaseConnectorUniversal-0.0.4.dist-info/RECORD
